ibm_agent_analytics/__init__.py
ibm_agent_analytics/instrumentation/__init__.py
ibm_agent_analytics/instrumentation/agent_analytics_sdk.py
ibm_agent_analytics/instrumentation/configs/__init__.py
ibm_agent_analytics/instrumentation/configs/otlp_collector_config.py
ibm_agent_analytics/instrumentation/traceloop/__init__.py
ibm_agent_analytics/instrumentation/traceloop/sdk/__init__.py
ibm_agent_analytics/instrumentation/traceloop/sdk/instruments.py
ibm_agent_analytics/instrumentation/traceloop/sdk/tracing/__init__.py
ibm_agent_analytics/instrumentation/traceloop/sdk/tracing/tracing.py
ibm_agent_analytics/instrumentation/traceloop/sdk/tracing/opentelemetry_instrumentation_crewai/__init__.py
ibm_agent_analytics/instrumentation/traceloop/sdk/tracing/opentelemetry_instrumentation_crewai/instrumentation.py
ibm_agent_analytics/instrumentation/traceloop/sdk/tracing/opentelemetry_instrumentation_crewai/patch.py
ibm_agent_analytics/instrumentation/traceloop/sdk/tracing/opentelemetry_instrumentation_crewai/utils.py
ibm_agent_analytics/instrumentation/traceloop/sdk/tracing/opentelemetry_instrumentation_crewai/version.py
ibm_agent_analytics/instrumentation/traceloop/sdk/tracing/opentelemetry_instrumentation_langchain/__init__.py
ibm_agent_analytics/instrumentation/traceloop/sdk/tracing/opentelemetry_instrumentation_langchain/callback_handler.py
ibm_agent_analytics/instrumentation/traceloop/sdk/tracing/opentelemetry_instrumentation_langchain/config.py
ibm_agent_analytics/instrumentation/traceloop/sdk/tracing/opentelemetry_instrumentation_langchain/event_emitter.py
ibm_agent_analytics/instrumentation/traceloop/sdk/tracing/opentelemetry_instrumentation_langchain/event_models.py
ibm_agent_analytics/instrumentation/traceloop/sdk/tracing/opentelemetry_instrumentation_langchain/span_utils.py
ibm_agent_analytics/instrumentation/traceloop/sdk/tracing/opentelemetry_instrumentation_langchain/utils.py
ibm_agent_analytics-0.5.9.dist-info/licenses/LICENSE
ibm_agent_analytics-0.5.9.dist-info/METADATA
ibm_agent_analytics-0.5.9.dist-info/WHEEL
ibm_agent_analytics-0.5.9.dist-info/top_level.txt
ibm_agent_analytics-0.5.9.dist-info/RECORD
