Metadata-Version: 2.4
Name: ibm_agent_analytics
Version: 0.5.9
Summary: Agent Analytics observability SDK package
Home-page: https://github.ibm.com/agent-analytics/sdk
Author: Muhammad Kanaan
Author-email: Muhammad.kanaan@ibm.com
License: International License Agreement for Non-Warranted Programs
Classifier: Programming Language :: Python :: 3
Classifier: Development Status :: 4 - Beta
Classifier: Natural Language :: English
Classifier: Programming Language :: Python :: 3.10
Classifier: Programming Language :: Python :: 3.11
Classifier: Programming Language :: Python :: 3.12
Classifier: Programming Language :: Python :: 3.13
Classifier: Operating System :: MacOS :: MacOS X
Classifier: Operating System :: POSIX :: Linux
Classifier: Operating System :: Microsoft :: Windows
Classifier: Intended Audience :: Science/Research
Classifier: Intended Audience :: Developers
Classifier: Intended Audience :: Information Technology
Classifier: Topic :: Software Development :: Libraries
Classifier: Topic :: Software Development :: Libraries :: Python Modules
Classifier: Topic :: Scientific/Engineering :: Artificial Intelligence
Classifier: Topic :: Scientific/Engineering :: Information Analysis
Requires-Python: >=3.10,<3.14
License-File: LICENSE
Requires-Dist: ibm-agent-analytics-common>=0.1.4
Requires-Dist: traceloop-sdk<0.45.0,>=0.40.6
Requires-Dist: langtrace-python-sdk==3.3.4
Requires-Dist: pydantic>=2.8.2
Requires-Dist: botocore
Requires-Dist: packaging
Requires-Dist: python-dotenv
Dynamic: author
Dynamic: author-email
Dynamic: classifier
Dynamic: description
Dynamic: description-content-type
Dynamic: home-page
Dynamic: license
Dynamic: license-file
Dynamic: requires-dist
Dynamic: requires-python
Dynamic: summary
